[
    {
      "model": "Т-150",
      "manufacturer": "Харьковский тракторный завод",
      "power": 150,
      "description": "Универсально-пропашной трактор",
      "image": "url_изображения_т150"
    },
    {
      "model": "К-700",
      "manufacturer": "Петербургский тракторный завод",
      "power": 300,
      "description": "Мощный сельскохозяйственный трактор",
      "image": "url_изображения_к700"
    },
    {
      "model": "Беларус-82.1",
      "manufacturer": "Минский тракторный завод",
      "power": 82,
      "description": "Универсальный трактор",
      "image": "url_изображения_беларус82"
    }
  ]